{
  "appPageId" : "18027216-8e7b-4872-a3ba-b6b48ac935cf",
  "componentName" : "siteforce:sldsOneColLayout",
  "id" : "4be411f8-4fdb-4ea5-86b8-83999596d92e",
  "label" : "Forgot Password",
  "regions" : [ {
    "components" : [ {
      "componentAttributes" : {
        "richTextValue" : "<div style=\"text-align: center;\"><span style=\"font-size:22px\">PASSWORD RESET</span></div>"
      },
      "componentName" : "forceCommunity:richTextInline",
      "id" : "8aefa2c8-52e6-41ad-a213-8f16077b01d1",
      "renderPriority" : "NEUTRAL",
      "renditionMap" : { },
      "type" : "component"
    }, {
      "componentAttributes" : {
        "richTextValue" : "<div style=\"text-align: center;\">To reset your password, we'll need your username.<br/> We'll send password reset instructions to the email address associated with your account.</div>"
      },
      "componentName" : "forceCommunity:richTextInline",
      "id" : "ca2d126e-c7b4-42ca-aec4-f59946f7b09e",
      "renderPriority" : "NEUTRAL",
      "renditionMap" : { },
      "type" : "component"
    }, {
      "componentAttributes" : {
        "checkEmailUrl" : "./CheckPasswordResetEmail",
        "submitButtonLabel" : "Reset Password",
        "usernameLabel" : "Username"
      },
      "componentName" : "salesforceIdentity:forgotPassword2",
      "id" : "6929b85a-e5f9-44ca-a88b-185a8f9179c2",
      "renderPriority" : "NEUTRAL",
      "renditionMap" : { },
      "type" : "component"
    }, {
      "componentAttributes" : {
        "richTextValue" : "<div style=\"text-align: center;\"><a href=\"./\">Cancel</a></div>"
      },
      "componentName" : "forceCommunity:richTextInline",
      "id" : "225698fa-4a9a-4ac3-b4f9-167a14a729f4",
      "renderPriority" : "NEUTRAL",
      "renditionMap" : { },
      "type" : "component"
    } ],
    "id" : "d26fb3bc-0dc1-47fe-9061-8df4f598290e",
    "regionName" : "content",
    "type" : "region"
  }, {
    "components" : [ {
      "componentAttributes" : {
        "description" : "",
        "metaTags" : "",
        "title" : "Forgot Password"
      },
      "componentName" : "forceCommunity:seoAssistant",
      "id" : "2ef9842b-9c1b-4a05-95e6-37dbe8fc8911",
      "renditionMap" : { },
      "type" : "component"
    } ],
    "id" : "b956e6c5-860c-4715-b6e1-4d4a1b8fb022",
    "regionName" : "sfdcHiddenRegion",
    "type" : "region"
  } ],
  "themeLayoutType" : "Login",
  "type" : "view",
  "viewType" : "forgot-password"
}